commie/__init__.py
commie/x01_common.py
commie/x01_errors.py
commie/x02_detector.py
commie/x03_glue.py
commie/parsers/__init__.py
commie/parsers/_helper.py
commie/parsers/c_parser_regex.py
commie/parsers/c_parser_state.py
commie/parsers/css_parser_regex.py
commie/parsers/html_parser_regex.py
commie/parsers/python_parser.py
commie/parsers/ruby_parser_regex.py
commie/parsers/shell_parser_state.py
commie/tests/__init__.py
commie/tests/c_test.py
commie/tests/css_test.py
commie/tests/go_test.py
commie/tests/helper.py
commie/tests/html_test.py
commie/tests/js_test.py
commie/tests/python_test.py
commie/tests/ruby_test.py
commie/tests/sass_test.py
commie/tests/shell_test.py
commie-1.0.6.post2.dist-info/LICENSE.txt
commie-1.0.6.post2.dist-info/METADATA
commie-1.0.6.post2.dist-info/WHEEL
commie-1.0.6.post2.dist-info/top_level.txt
commie-1.0.6.post2.dist-info/RECORD
