Metadata-Version: 2.1
Name: commie
Version: 1.0.6.post2
Summary: Extracts comments from source code in different programming languages
Home-page: https://github.com/rtmigo/commie_py
Author: Artёm IG
Author-email: ortemeo@gmail.com
License: BSD-3-Clause
Keywords: css,python,c,search,java,go,html,sass,c-sharp,dart,bash,parser,typescript,parsing,xml,comments,source-code
Platform: UNKNOWN
Classifier: Intended Audience :: Developers
Classifier: License :: OSI Approved :: BSD License
Classifier: Topic :: Software Development :: Documentation
Classifier: Programming Language :: Python :: 3.7
Classifier: Programming Language :: Python :: 3.8
Classifier: Programming Language :: Python :: 3.9
Classifier: Programming Language :: Python :: 3.10
Classifier: Operating System :: OS Independent
License-File: LICENSE.txt
